blackspammerbd/__init__.py
blackspammerbd/cli.py
blackspammerbd/core.py
blackspammerbd/persistence.py
blackspammerbd/teligram.py
blackspammerbd_vx1-1.0.0.dist-info/LICENSE
blackspammerbd_vx1-1.0.0.dist-info/METADATA
blackspammerbd_vx1-1.0.0.dist-info/WHEEL
blackspammerbd_vx1-1.0.0.dist-info/entry_points.txt
blackspammerbd_vx1-1.0.0.dist-info/top_level.txt
blackspammerbd_vx1-1.0.0.dist-info/RECORD
